docker_tools_plus/__init__.py
docker_tools_plus/cli.py
docker_tools_plus/database.py
docker_tools_plus/exceptions.py
docker_tools_plus/settings.py
docker_tools_plus-0.5.1.dist-info/entry_points.txt
docker_tools_plus-0.5.1.dist-info/licenses/LICENSE
docker_tools_plus-0.5.1.dist-info/WHEEL
docker_tools_plus-0.5.1.dist-info/METADATA
docker_tools_plus-0.5.1.dist-info/RECORD
