Metadata-Version: 2.4
Name: docker-tools-plus
Version: 0.5.1
Summary: CLI tool for managing Docker container cleanups
Requires-Python: >=3.10
License-File: LICENSE
Requires-Dist: click>=8.1.0
Requires-Dist: pydantic>=2.0
Requires-Dist: tomli>=2.0.0
Requires-Dist: python-dotenv>=0.19.0
Requires-Dist: pytest>=8.0.0 ; extra == "dev"
Requires-Dist: pytest-cov>=4.0.0 ; extra == "dev"
Requires-Dist: pytest-mock>=3.0.0 ; extra == "dev"
Requires-Dist: ruff>=0.3.0 ; extra == "dev"
Requires-Dist: coverage>=7.0.0 ; extra == "dev"
Requires-Dist: twine>=6.1.0 ; extra == "dev"
Project-URL: Homepage, https://github.com/luiscberrocal/docker-tools-plus
Project-URL: Repository, https://github.com/luiscberrocal/docker-tools-plus
Provides-Extra: dev
